LICENSE
MANIFEST.in
README.rst
setup.py
variadic.py
variadic.egg-info/PKG-INFO
variadic.egg-info/SOURCES.txt
variadic.egg-info/dependency_links.txt
variadic.egg-info/top_level.txt